README.md
setup.py
ip2as/__init__.py
ip2as/format_caida.py
ip2as/ip2as.py
ip2as/ip2ases.py
ip2as/ixponly.py
ip2as/prefix2as.py
ip2as/prefixes.py
ip2as/reserved.py
ip2as/rir_delegations.py
ip2as/whois2as.py
ip2as.egg-info/PKG-INFO
ip2as.egg-info/SOURCES.txt
ip2as.egg-info/dependency_links.txt
ip2as.egg-info/entry_points.txt
ip2as.egg-info/not-zip-safe
ip2as.egg-info/requires.txt
ip2as.egg-info/top_level.txt