Metadata-Version: 2.1
Name: ip2as
Version: 0.1.1
Summary: Create prefix-to-AS mappings.
Home-page: https://github.com/alexmarder/ip2as
Author: Alex Marder
Requires-Python: >3.6
